{
	"configuration": {
		"className": "com.liferay.object.admin.rest.dto.v1_0.ObjectDefinition",
		"multiCompany": true,
		"parameters": {
			"containsHeaders": "true",
			"createStrategy": "UPSERT",
			"featureFlag": "LPS-164563",
			"importStrategy": "ON_ERROR_FAIL",
			"updateStrategy": "UPDATE"
		},
		"taskItemDelegateName": "DEFAULT",
		"userId": 0,
		"version": "v1.0"
	},
	"items": [
		{
			"enableLocalization": true,
			"externalReferenceCode": "L_DATA_SET_DATE_FILTER",
			"label": {
				"en_US": "Data Set Date Filter"
			},
			"modifiable": true,
			"name": "DataSetDateFilter",
			"objectActions": [
			],
			"objectFields": [
				{
					"DBType": "String",
					"businessType": "Text",
					"externalReferenceCode": "FIELD_NAME",
					"indexed": true,
					"indexedAsKeyword": false,
					"label": {
						"en_US": "Field Name"
					},
					"localized": false,
					"name": "fieldName",
					"readOnly": "false",
					"required": true,
					"state": false,
					"system": true,
					"type": "String",
					"unique": false
				},
				{
					"DBType": "Date",
					"businessType": "Date",
					"externalReferenceCode": "FROM_DATE",
					"indexed": true,
					"indexedAsKeyword": false,
					"label": {
						"en_US": "From Date"
					},
					"localized": false,
					"name": "fromDate",
					"readOnly": "false",
					"required": false,
					"state": false,
					"system": true,
					"type": "Date",
					"unique": false
				},
				{
					"DBType": "String",
					"businessType": "Text",
					"externalReferenceCode": "LABEL",
					"indexed": true,
					"indexedAsKeyword": false,
					"label": {
						"en_US": "Label"
					},
					"localized": true,
					"name": "label",
					"readOnly": "false",
					"required": false,
					"state": false,
					"system": true,
					"type": "String",
					"unique": false
				},
				{
					"DBType": "Date",
					"businessType": "Date",
					"externalReferenceCode": "TO_DATE",
					"indexed": true,
					"indexedAsKeyword": false,
					"label": {
						"en_US": "To Date"
					},
					"localized": false,
					"name": "toDate",
					"readOnly": "false",
					"required": false,
					"state": false,
					"system": true,
					"type": "Date",
					"unique": false
				},
				{
					"DBType": "String",
					"businessType": "Text",
					"externalReferenceCode": "TYPE",
					"indexed": true,
					"indexedAsKeyword": false,
					"label": {
						"en_US": "Type"
					},
					"localized": false,
					"name": "type",
					"readOnly": "false",
					"required": false,
					"state": false,
					"system": true,
					"type": "String",
					"unique": false
				}
			],
			"objectFolderExternalReferenceCode": "default",
			"panelCategoryKey": "",
			"parameterRequired": false,
			"pluralLabel": {
				"en_US": "Data Set Date Filters"
			},
			"portlet": false,
			"scope": "company",
			"status": {
				"code": 2
			},
			"system": true
		}
	]
}