{
	"configuration": {
		"className": "com.liferay.object.admin.rest.dto.v1_0.ObjectDefinition",
		"parameters": {
			"containsHeaders": "true",
			"createStrategy": "UPSERT",
			"importStrategy": "ON_ERROR_FAIL",
			"updateStrategy": "UPDATE"
		},
		"taskItemDelegateName": "DEFAULT"
	},
	"items": [
		{
			"accountEntryRestricted": false,
			"active": true,
			"enableCategorization": true,
			"enableComments": false,
			"enableObjectEntryHistory": false,
			"externalReferenceCode": "HS10_COMPANY",
			"label": {
				"en_US": "HS10 Company"
			},
			"name": "HS10Company",
			"objectActions": [
				{
					"active": true,
					"label": {
						"en_US": "Liferay HubSpot Etc Spring Boot Object Action Company"
					},
					"name": "SpringBootObjectActionCompany",
					"objectActionExecutorKey": "function#liferay-hubspot-etc-spring-boot-object-action-company",
					"objectActionTriggerKey": "onAfterAdd",
					"parameters": {
					},
					"status": {
						"code": 0,
						"label": "never-ran",
						"label_i18n": "Never Ran"
					}
				}
			],
			"objectFields": [
				{
					"DBType": "String",
					"businessType": "Text",
					"externalReferenceCode": "NAME",
					"indexed": true,
					"indexedAsKeyword": false,
					"indexedLanguageId": "en_US",
					"label": {
						"en_US": "Name"
					},
					"name": "name",
					"objectFieldSettings": [
						{
							"name": "showCounter",
							"value": false
						}
					],
					"required": false,
					"state": false,
					"system": false,
					"type": "String"
				},
				{
					"DBType": "Long",
					"businessType": "LongInteger",
					"externalReferenceCode": "NUMBER_OF_EMPLOYEES",
					"indexed": true,
					"indexedAsKeyword": false,
					"indexedLanguageId": "",
					"label": {
						"en_US": "Number of Employees"
					},
					"name": "numberOfEmployees",
					"objectFieldSettings": [
					],
					"required": false,
					"state": false,
					"system": false,
					"type": "Long"
				},
				{
					"DBType": "String",
					"businessType": "Text",
					"externalReferenceCode": "PHONE",
					"indexed": true,
					"indexedAsKeyword": false,
					"indexedLanguageId": "en_US",
					"label": {
						"en_US": "Phone"
					},
					"name": "phone",
					"objectFieldSettings": [
						{
							"name": "showCounter",
							"value": false
						}
					],
					"required": false,
					"state": false,
					"system": false,
					"type": "String"
				},
				{
					"DBType": "String",
					"businessType": "Text",
					"externalReferenceCode": "WEBSITE",
					"indexed": true,
					"indexedAsKeyword": false,
					"indexedLanguageId": "en_US",
					"label": {
						"en_US": "Website"
					},
					"name": "website",
					"objectFieldSettings": [
						{
							"name": "showCounter",
							"value": false
						}
					],
					"required": false,
					"state": false,
					"system": false,
					"type": "String"
				}
			],
			"objectFolderExternalReferenceCode": "HS10_HUBSPOT",
			"panelCategoryKey": "control_panel.object",
			"parameterRequired": false,
			"pluralLabel": {
				"en_US": "HS10 Companies"
			},
			"portlet": true,
			"restContextPath": "/o/c/hs10companies",
			"scope": "company",
			"status": {
				"code": 0,
				"label": "approved",
				"label_i18n": "Approved"
			}
		},
		{
			"accountEntryRestricted": false,
			"active": true,
			"enableCategorization": true,
			"enableComments": false,
			"enableObjectEntryHistory": false,
			"externalReferenceCode": "HS10_CONTACT",
			"label": {
				"en_US": "HS10 Contact"
			},
			"name": "HS10Contact",
			"objectActions": [
				{
					"active": true,
					"label": {
						"en_US": "Liferay HubSpot Etc Spring Boot Object Action Contact"
					},
					"name": "SpringBootObjectActionContact",
					"objectActionExecutorKey": "function#liferay-hubspot-etc-spring-boot-object-action-contact",
					"objectActionTriggerKey": "onAfterAdd",
					"parameters": {
					},
					"status": {
						"code": 0,
						"label": "never-ran",
						"label_i18n": "Never Ran"
					}
				}
			],
			"objectFields": [
				{
					"DBType": "String",
					"businessType": "Text",
					"externalReferenceCode": "EMAIL",
					"indexed": true,
					"indexedAsKeyword": false,
					"indexedLanguageId": "en_US",
					"label": {
						"en_US": "Email"
					},
					"name": "email",
					"objectFieldSettings": [
						{
							"name": "showCounter",
							"value": false
						}
					],
					"required": false,
					"state": false,
					"system": false,
					"type": "String"
				},
				{
					"DBType": "String",
					"businessType": "Text",
					"externalReferenceCode": "FIRST_NAME",
					"indexed": true,
					"indexedAsKeyword": false,
					"indexedLanguageId": "en_US",
					"label": {
						"en_US": "First Name"
					},
					"name": "firstName",
					"objectFieldSettings": [
						{
							"name": "showCounter",
							"value": false
						}
					],
					"required": false,
					"state": false,
					"system": false,
					"type": "String"
				},
				{
					"DBType": "String",
					"businessType": "Text",
					"externalReferenceCode": "LAST_NAME",
					"indexed": true,
					"indexedAsKeyword": false,
					"indexedLanguageId": "en_US",
					"label": {
						"en_US": "Last Name"
					},
					"name": "lastName",
					"objectFieldSettings": [
						{
							"name": "showCounter",
							"value": false
						}
					],
					"required": false,
					"state": false,
					"system": false,
					"type": "String"
				},
				{
					"DBType": "String",
					"businessType": "Text",
					"externalReferenceCode": "PHONE",
					"indexed": true,
					"indexedAsKeyword": false,
					"indexedLanguageId": "en_US",
					"label": {
						"en_US": "Phone"
					},
					"name": "phone",
					"objectFieldSettings": [
						{
							"name": "showCounter",
							"value": false
						}
					],
					"required": false,
					"state": false,
					"system": false,
					"type": "String"
				}
			],
			"objectFolderExternalReferenceCode": "HS10_HUBSPOT",
			"objectRelationships": [
				{
					"deletionType": "disassociate",
					"externalReferenceCode": "HS10_CONTACT_TO_HS10_LEADS",
					"label": {
						"en_US": "HS10 Contact to HS10 Leads"
					},
					"name": "hs10ContactToHS10Leads",
					"objectDefinitionExternalReferenceCode1": "HS10_CONTACT",
					"objectDefinitionExternalReferenceCode2": "HS10_LEAD",
					"type": "oneToMany"
				}
			],
			"panelCategoryKey": "control_panel.object",
			"parameterRequired": false,
			"pluralLabel": {
				"en_US": "HS10 Contacts"
			},
			"portlet": true,
			"restContextPath": "/o/c/hs10contacts",
			"scope": "company",
			"status": {
				"code": 0,
				"label": "approved",
				"label_i18n": "Approved"
			}
		},
		{
			"accountEntryRestricted": false,
			"active": true,
			"enableCategorization": true,
			"enableComments": false,
			"enableObjectEntryHistory": false,
			"externalReferenceCode": "HS10_LEAD",
			"label": {
				"en_US": "HS10 Lead"
			},
			"name": "HS10Lead",
			"objectActions": [
				{
					"active": true,
					"label": {
						"en_US": "Liferay HubSpot Etc Spring Boot Object Action Lead"
					},
					"name": "SpringBootObjectActionLead",
					"objectActionExecutorKey": "function#liferay-hubspot-etc-spring-boot-object-action-lead",
					"objectActionTriggerKey": "onAfterAdd",
					"parameters": {
					},
					"status": {
						"code": 0,
						"label": "never-ran",
						"label_i18n": "Never Ran"
					}
				}
			],
			"objectFields": [
				{
					"DBType": "String",
					"businessType": "Picklist",
					"externalReferenceCode": "HS_LEAD_LABEL",
					"indexed": true,
					"indexedAsKeyword": false,
					"indexedLanguageId": "en_US",
					"label": {
						"en_US": "HS Lead Label"
					},
					"listTypeDefinitionExternalReferenceCode": "HS10_LEAD_LABEL",
					"name": "hsLeadLabel",
					"objectFieldSettings": [
					],
					"required": true,
					"state": false,
					"system": false,
					"type": "String"
				},
				{
					"DBType": "String",
					"businessType": "Text",
					"externalReferenceCode": "HS_LEAD_NAME",
					"indexed": true,
					"indexedAsKeyword": false,
					"indexedLanguageId": "en_US",
					"label": {
						"en_US": "HS Lead Name"
					},
					"name": "hsLeadName",
					"objectFieldSettings": [
						{
							"name": "showCounter",
							"value": false
						}
					],
					"required": false,
					"state": false,
					"system": false,
					"type": "String"
				},
				{
					"DBType": "String",
					"businessType": "Picklist",
					"externalReferenceCode": "HS_LEAD_TYPE",
					"indexed": true,
					"indexedAsKeyword": false,
					"indexedLanguageId": "en_US",
					"label": {
						"en_US": "HS Lead Type"
					},
					"listTypeDefinitionExternalReferenceCode": "HS10_LEAD_TYPE",
					"name": "hsLeadType",
					"objectFieldSettings": [
					],
					"required": true,
					"state": false,
					"system": false,
					"type": "String"
				}
			],
			"objectFolderExternalReferenceCode": "HS10_HUBSPOT",
			"panelCategoryKey": "control_panel.object",
			"parameterRequired": false,
			"pluralLabel": {
				"en_US": "HS10 Leads"
			},
			"portlet": true,
			"restContextPath": "/o/c/hs10leads",
			"scope": "company",
			"status": {
				"code": 0,
				"label": "approved",
				"label_i18n": "Approved"
			}
		}
	]
}