[
	{
		"regionCode": "AN",
		"name": "Andalusia",
		"active_": true
	},
	{
		"regionCode": "AR",
		"name": "Aragon",
		"active_": true
	},
	{
		"regionCode": "AS",
		"name": "Asturias",
		"active_": true
	},
	{
		"regionCode": "IB",
		"name": "Balearic Islands",
		"active_": true
	},
	{
		"regionCode": "PV",
		"name": "Basque Country",
		"active_": true
	},
	{
		"regionCode": "CN",
		"name": "Canary Islands",
		"active_": true
	},
	{
		"regionCode": "CB",
		"name": "Cantabria",
		"active_": true
	},
	{
		"regionCode": "CL",
		"name": "Castile and Leon",
		"active_": true
	},
	{
		"regionCode": "CM",
		"name": "Castile-La Mancha",
		"active_": true
	},
	{
		"regionCode": "CT",
		"name": "Catalonia",
		"active_": true
	},
	{
		"regionCode": "CE",
		"name": "Ceuta",
		"active_": true
	},
	{
		"regionCode": "EX",
		"name": "Extremadura",
		"active_": true
	},
	{
		"regionCode": "GA",
		"name": "Galicia",
		"active_": true
	},
	{
		"regionCode": "LO",
		"name": "La Rioja",
		"active_": true
	},
	{
		"regionCode": "M",
		"name": "Madrid",
		"active_": true
	},
	{
		"regionCode": "ML",
		"name": "Melilla",
		"active_": true
	},
	{
		"regionCode": "MU",
		"name": "Murcia",
		"active_": true
	},
	{
		"regionCode": null,
		"name": "Navarra",
		"active_": true
	},
	{
		"regionCode": "VC",
		"name": "Valencia",
		"active_": true
	}
]